trad_setlist_helper/__init__.py
trad_setlist_helper/html.py
trad_setlist_helper/py.typed
trad_setlist_helper-0.0.1.dist-info/METADATA
trad_setlist_helper-0.0.1.dist-info/WHEEL
trad_setlist_helper-0.0.1.dist-info/licenses/LICENSE
trad_setlist_helper-0.0.1.dist-info/RECORD
