Metadata-Version: 2.4
Name: trad-setlist-helper
Version: 0.0.1
Summary: Convert list of tune sets to setlist with incipits
Author-email: zmoon <zmoon92@gmail.com>
License: This is free and unencumbered software released into the public domain.
License-File: LICENSE
Requires-Python: ~=3.11
Requires-Dist: pandas
Requires-Dist: pyabc2
